d_link/__init__.py
d_link/configure.py
d_link/data_extractor.py
d_link/github_pusher.py
d_link/settings.py
d_link/settings_manager.py
d_link-0.2.4.dist-info/METADATA
d_link-0.2.4.dist-info/WHEEL
d_link-0.2.4.dist-info/entry_points.txt
d_link-0.2.4.dist-info/top_level.txt
d_link-0.2.4.dist-info/RECORD
