Metadata-Version: 2.1
Name: d-link
Version: 0.2.4
Summary: A Python library to extract data from a Python script and push it to a GitHub Pages repository.
Home-page: https://github.com/PgNetwork01/d-link
Author: Pg Network
Author-email: gamerzp780@gmail.com
Classifier: Programming Language :: Python :: 3
Classifier: License :: OSI Approved :: MIT License
Classifier: Operating System :: OS Independent
Requires-Python: >=3.6
